LICENSE
MANIFEST.in
README.rst
setup.py
sphinx_dehead/__init__.py
sphinx_dehead.egg-info/PKG-INFO
sphinx_dehead.egg-info/SOURCES.txt
sphinx_dehead.egg-info/dependency_links.txt
sphinx_dehead.egg-info/entry_points.txt
sphinx_dehead.egg-info/requires.txt
sphinx_dehead.egg-info/top_level.txt