Metadata-Version: 1.1
Name: sphinx-dehead
Version: 0.2.1
Summary: A script to extract the main div section element from HTML
Home-page: http://github.com/shidarin/dehead
Author: Sean Wallitsch
Author-email: sean@grenadehop.com
License: MIT
Keywords: sphinx bootstrap octopress html rst partial
Platform: any
Classifier: Development Status :: 3 - Alpha
Classifier: Environment :: Console
Classifier: Intended Audience :: End Users/Desktop
Classifier: Intended Audience :: Developers
Classifier: Topic :: Text Processing :: Markup :: HTML
Classifier: Topic :: Internet :: WWW/HTTP :: Dynamic Content
Classifier: License :: OSI Approved :: MIT License
Classifier: Programming Language :: Python :: 2.6
Classifier: Programming Language :: Python :: 2.7
Classifier: Programming Language :: Python :: Implementation :: CPython
Classifier: Operating System :: OS Independent
Classifier: Natural Language :: English
